{"status":{"version":"1.0.0","code":0,"msg":"SuccessWithResult","total":1,"page":1,"pagesize":10,"transactionID":"6d2395dd2f06ecf84074eba7db863dee"},"echoed_fields":{"jobID":"","loanNumber":"","preparedBy":"","resellerID":"","preparedFor":""},"property":[{"identifier":{"Id":217697972,"fips":"27053","apn":"25-118-23-13-0009","attomId":217697972},"lot":{"frontage":300.0,"lotNum":"2","lotSize1":7.5,"lotSize2":326700.0,"zoningType":"Residential"},"area":{"countrySecSubd":"Hennepin","subdName":"HUNTER RIDGE FARM","censusTractIdent":"27101","censusBlockGroup":"1"},"address":{"country":"US","countrySubd":"MN","line1":"1382 HUNTER DR","line2":"WAYZATA, MN 55391","locality":"WAYZATA","matchCode":"ExaStr","oneLine":"1382 HUNTER DR, WAYZATA, MN 55391","postal1":"55391","postal2":"9657","postal3":"R012"},"location":{"accuracy":"Rooftop","latitude":"45.003351","longitude":"-93.527410","distance":0.0,"geoid":"CO27053, CS2741480, DB2725080, PL2741480, SB0000095687, SB0000095688, SB0000095689, SB0000095690, SB0000144289, ZI55391","geoIdV4":{"CO":"b8281c1866cb34a5104ce0546d1a03ee","CS":"25f910ed3c0fbd344d8d7b0bffba1f67","DB":"07810be3ce206785a1d5773fc43990db","PL":"957015b9a66664be8ab4c482ccf466b4","SB":"2ce28ea969a5d0f1ea9aad8993a47dc7,99687e3915277833a42091179fdb0d24,eab715d3c687c859d376e7529884e2bc","ZI":"da9a12a10824ff7f808f4613f4ca0b43"}},"summary":{"absenteeInd":"OWNER OCCUPIED","propClass":"Single Family Residence / Townhouse","propSubType":"Residential","propType":"SFR","yearBuilt":1960,"propLandUse":"SFR","propIndicator":10,"legal1":"002 001 HUNTER RIDGE FARM IRREGULAR"},"utilities":{"coolingType":"PACKAGE","energyType":"AVERAGE","heatingFuel":"ELECTRIC","heatingType":"FLOOR/WALL FURNACE","wallType":"WOOD"},"sale":{"saleSearchDate":"2020-09-25","saleTransDate":"2020-09-10","transactionIdent":"912870825","saleAmountData":{"saleAmt":1900000.0,"saleRecDate":"2020-09-25","saleDisclosureType":0,"saleDocType":"DEED","saleDocNum":"0005750162","saleTransType":"Resale"}},"building":{"size":{"bldgSize":3299.0,"grossSize":5085.0,"grossSizeAdjusted":3299.0,"groundFloorSize":3341.0,"livingSize":3299.0,"sizeInd":"LIVING SQFT","universalSize":3299.0},"rooms":{"bathsFull":2,"bathsPartial":4,"bathsTotal":6.0,"beds":5,"roomsTotal":10},"interior":{"bsmtSize":1786,"bsmtType":"FINISHED","floors":"WOOD (UNSPECIFIED)","fplcCount":2,"fplcInd":"Y","fplcType":"YES","bsmtFinishedPercent":89},"construction":{"condition":"GOOD","foundationType":"CONCRETE BLOCK"},"parking":{"garageType":"Garage, Attached","prkgSize":884.0,"prkgType":"Garage, Attached"},"summary":{"levels":1,"unitsCount":1,"view":"VIEW - NONE","viewCode":"000"}},"assessment":{"appraised":{},"assessed":{"assdImprValue":812000.0,"assdLandValue":1062000.0,"assdTtlValue":1874000.0},"market":{"mktImprValue":812000.0,"mktLandValue":1062000.0,"mktTtlValue":1874000.0},"tax":{"taxAmt":24272.16,"taxPerSizeUnit":7.36,"taxYear":2022.0,"exemption":{},"exemptiontype":{"Homeowner":"Y"}},"improvementPercent":43,"owner":{"corporateIndicator":"N","owner1":{"lastName":"SPECKS ","firstNameAndMi":"MARKUS "},"owner2":{},"owner3":{},"owner4":{},"absenteeOwnerStatus":"O","mailingAddressOneLine":"1382 HUNTER DR, WAYZATA, MN 55391-9657"},"mortgage":{"FirstConcurrent":{"trustDeedDocumentNumber":"5750167","amount":1415625.0,"lenderLastName":"WELLS FARGO BK"},"SecondConcurrent":{}}},"vintage":{"lastModified":"2022-09-21","pubDate":"2022-09-21"}}]}
